mirar/__init__.py
mirar/__main__.py
mirar/catalog/__init__.py
mirar/catalog/base/__init__.py
mirar/catalog/base/base_catalog.py
mirar/catalog/base/base_gaia.py
mirar/catalog/base/base_xmatch_catalog.py
mirar/catalog/base/catalog_from_file.py
mirar/catalog/base/errors.py
mirar/catalog/kowalski/__init__.py
mirar/catalog/kowalski/base_kowalski_catalog.py
mirar/catalog/kowalski/gaia.py
mirar/catalog/kowalski/ps1.py
mirar/catalog/kowalski/tmass.py
mirar/catalog/kowalski/ztf.py
mirar/catalog/multibackend/__init__.py
mirar/catalog/multibackend/gaia2mass.py
mirar/catalog/tap/__init__.py
mirar/catalog/tap/gaia2mass.py
mirar/catalog/vizier/__init__.py
mirar/catalog/vizier/base_vizier_catalog.py
mirar/catalog/vizier/gaia2mass.py
mirar/catalog/vizier/ps1.py
mirar/catalog/vizier/sdss.py
mirar/catalog/vizier/skymapper.py
mirar/data/__init__.py
mirar/data/base_data.py
mirar/data/cache.py
mirar/data/image_data.py
mirar/data/source_data.py
mirar/data/utils/__init__.py
mirar/data/utils/compress.py
mirar/data/utils/coords.py
mirar/data/utils/plot_image.py
mirar/database/__init__.py
mirar/database/base_model.py
mirar/database/base_table.py
mirar/database/constants.py
mirar/database/constraints.py
mirar/database/credentials.py
mirar/database/engine.py
mirar/database/errors.py
mirar/database/q3c.py
mirar/database/setup.py
mirar/database/transactions/__init__.py
mirar/database/transactions/insert.py
mirar/database/transactions/select.py
mirar/database/transactions/update.py
mirar/database/user/__init__.py
mirar/database/user/postgres_admin.py
mirar/database/user/postgres_user.py
mirar/database/utils.py
mirar/downloader/__init__.py
mirar/downloader/caltech.py
mirar/downloader/get_test_data.py
mirar/errors/__init__.py
mirar/errors/error_report.py
mirar/errors/error_stack.py
mirar/errors/exceptions.py
mirar/io.py
mirar/monitor/__init__.py
mirar/monitor/base_monitor.py
mirar/paths.py
mirar/pipelines/__init__.py
mirar/pipelines/base_pipeline.py
mirar/pipelines/git/blocks.py
mirar-1.0.0.dist-info/METADATA
mirar-1.0.0.dist-info/WHEEL
mirar-1.0.0.dist-info/entry_points.txt
mirar-1.0.0.dist-info/licenses/LICENSE
mirar-1.0.0.dist-info/RECORD
